pepelatepeh/__init__.py
pepelatepeh/latex_table.py
pepelatepeh-0.1.3.dist-info/METADATA
pepelatepeh-0.1.3.dist-info/WHEEL
pepelatepeh-0.1.3.dist-info/top_level.txt
pepelatepeh-0.1.3.dist-info/RECORD
